README.md
setup.py
criteo_marketing/__init__.py
criteo_marketing/api_client.py
criteo_marketing/configuration.py
criteo_marketing/exceptions.py
criteo_marketing/rest.py
criteo_marketing.egg-info/PKG-INFO
criteo_marketing.egg-info/SOURCES.txt
criteo_marketing.egg-info/dependency_links.txt
criteo_marketing.egg-info/requires.txt
criteo_marketing.egg-info/top_level.txt
criteo_marketing/api/__init__.py
criteo_marketing/api/advertisers_api.py
criteo_marketing/api/audiences_api.py
criteo_marketing/api/authentication_api.py
criteo_marketing/api/budgets_api.py
criteo_marketing/api/campaigns_api.py
criteo_marketing/api/categories_api.py
criteo_marketing/api/portfolio_api.py
criteo_marketing/api/publishers_api.py
criteo_marketing/api/sellers_api.py
criteo_marketing/api/sellers_v2_api.py
criteo_marketing/api/sellers_v2_stats_api.py
criteo_marketing/api/statistics_api.py
criteo_marketing/models/__init__.py
criteo_marketing/models/advertiser_campaign_message.py
criteo_marketing/models/advertiser_info_message.py
criteo_marketing/models/advertiser_quota_message.py
criteo_marketing/models/audience_create_request.py
criteo_marketing/models/audience_create_response.py
criteo_marketing/models/audience_patch_request.py
criteo_marketing/models/audience_patch_response.py
criteo_marketing/models/audience_put_request.py
criteo_marketing/models/audience_response.py
criteo_marketing/models/audiences_get_response.py
criteo_marketing/models/bid_message.py
criteo_marketing/models/budget_message.py
criteo_marketing/models/campaign_bid_change_request.py
criteo_marketing/models/campaign_bid_change_response.py
criteo_marketing/models/campaign_bid_message.py
criteo_marketing/models/campaign_message.py
criteo_marketing/models/campaign_report_query_message.py
criteo_marketing/models/catalog_product.py
criteo_marketing/models/catalog_product_v3.py
criteo_marketing/models/category_bid_change_request.py
criteo_marketing/models/category_bid_message.py
criteo_marketing/models/category_message.py
criteo_marketing/models/category_update_error.py
criteo_marketing/models/category_update_input.py
criteo_marketing/models/category_updates_per_catalog.py
